[
  {
    "image": "https://cdn11.bigcommerce.com/s-mpabgyqav0/images/stencil/500x659/products/365/3355/Acai_Berry_Frost_-_1__69723.1695139899.jpg?c=1",
    "images": [
      "https://cdn11.bigcommerce.com/s-mpabgyqav0/images/stencil/1280x1280/products/365/3308/Indoor_-_THCa_Acai_Berry_Frost_Terpenes__54128.1695139895.jpg?c=1",
      "https://cdn11.bigcommerce.com/s-mpabgyqav0/images/stencil/1280x1280/products/365/3307/Indoor_-_THCa_Acai_Berry_Frost_Potency__49509.1695139895.jpg?c=1"
    ],
    "terpenes": [],
    "vendor": "WNC",
    "cannabinoids": [
      {
        "pct": "20.473",
        "originalText": "Total 20473 204.729",
        "name": "Total Cannabinoids",
        "mgg": "204.729"
      },
      {
        "pct": "19.856",
        "originalText": "A-9-Tetrahydrocannabinolic Acid (THCA-A) 0.0485 0.0728 19.856 198.563",
        "name": "Unreadable",
        "mgg": "198.563"
      },
      {
        "pct": "0.405",
        "originalText": "Cannabigerolic Acid (CBGA) 0.0485 0.0728 0.405 4.049",
        "name": "CBGA",
        "mgg": "4.049"
      },
      {
        "pct": "0.121",
        "originalText": "Cannabichromenic Acid (CBCA) 0.0485 0.0728 0.121 1214",
        "name": "CBCA",
        "mgg": "1214"
      },
      {
        "pct": "0.090",
        "originalText": "A-9-Tetrahydrocannabinol (A-9 THC) 0.0485 0.0728 0.090 0.903",
        "name": "Unreadable",
        "mgg": "0.903"
      },
      {
        "pct": "0.000",
        "originalText": "A-8-Tetrahydrocannabinol (A-8 THC) 0.0485 0.0728 ND ND",
        "name": "Unreadable",
        "mgg": 0
      },
      {
        "pct": "0.000",
        "originalText": "A-9-Tetrahydrocannabiphorol (A-9-THCP) 0.0485 0.0728 ND ND",
        "name": "THCP",
        "mgg": 0
      },
      {
        "pct": "0.000",
        "originalText": "A-9-Tetrahydrocannabivarin (A-9-THCV) 0.0485 0.0728 ND ND",
        "name": "THCV",
        "mgg": 0
      },
      {
        "pct": "0.000",
        "originalText": "A-9-Tetrahydrocannabivarinic Acid (A-9-THCVA) 0.0485 0.0728 <LOQ <LOQ",
        "name": "Delta 9-THCVA",
        "mgg": 0
      },
      {
        "pct": "0.000",
        "originalText": "R-A-10-Tetrahydrocannabinol (R-A-10-THC) 0.0485 0.0728 ND ND",
        "name": "R-Delta 10-THC",
        "mgg": 0
      },
      {
        "pct": "0.000",
        "originalText": "$-A-10-Tetrahydrocannabinol (S-A-10-THC) 0.0485 0.0728 ND ND",
        "name": "S-Delta 10-THC",
        "mgg": 0
      },
      {
        "pct": "0.000",
        "originalText": "9R-Hexahydrocannabinol (9R-HHC) 0.0485 0.0728 ND ND",
        "name": "9R-HHC",
        "mgg": 0
      },
      {
        "pct": "0.000",
        "originalText": "9S-Hexahydrocannabinol (95-HHC) 0.0485 0.0728 ND ND",
        "name": "9S-HHC",
        "mgg": 0
      },
      {
        "pct": "0.000",
        "originalText": "Tetrahydrocannabinol Acetate (THCO) 0.0485 0.0728 ND ND",
        "name": "THC",
        "mgg": 0
      },
      {
        "pct": "0.000",
        "originalText": "Cannabidivarin (CBDV) 0.0485 0.0728 ND ND",
        "name": "CBDV",
        "mgg": 0
      },
      {
        "pct": "0.000",
        "originalText": "Cannabidivarinic Acid (CBDVA) 0.0485 0.0728 ND ND",
        "name": "CBDVA",
        "mgg": 0
      },
      {
        "pct": "0.000",
        "originalText": "Cannabidiol (CBD) 0.0485 0.0728 ND ND",
        "name": "CBD",
        "mgg": 0
      },
      {
        "pct": "0.000",
        "originalText": "Cannabidiolic Acid (CBDA) 0.0485 0.0728 ND ND",
        "name": "CBDA",
        "mgg": 0
      },
      {
        "pct": "0.000",
        "originalText": "Cannabigerol (CBG) 0.0204 0.0728 <LOQ <L0Q",
        "name": "CBG",
        "mgg": 0
      },
      {
        "pct": "0.000",
        "originalText": "Cannabinol (CBN) 0.0485 0.0728 ND ND",
        "name": "CBN",
        "mgg": 0
      },
      {
        "pct": "0.000",
        "originalText": "Cannabinolic Acid (CBNA) 0.0485 0.0728 ND ND",
        "name": "CBNA",
        "mgg": 0
      },
      {
        "pct": "0.000",
        "originalText": "Cannabichromene (CBC) 0.0485 0.0728 ND ND",
        "name": "CBC",
        "mgg": 0
      },
      {
        "pct": "NaN",
        "originalText": "HC = THCa * 0.877 + A9-THC:Total CBD = CBDa * 0.877 + CBD; LOQ = Limit of Quantitation; ND = Not Detected.",
        "name": "Unreadable",
        "mgg": "Detected."
      },
      {
        "pct": "NaN",
        "originalText": "Unknown",
        "name": "Unreadable",
        "mgg": 0
      }
    ],
    "variants": [
      "3.5 g",
      "7 g"
    ],
    "title": "Acai Berry Frost",
    "url": "https://wnc-cbd.com/products/thca-acai-berry-frost-indoor-living-soil.html"
  },
  {
    "image": "https://cdn11.bigcommerce.com/s-mpabgyqav0/images/stencil/500x659/products/312/2452/Alien_Apple_Kush_-_1__91421.1689092161.jpg?c=1",
    "images": [
      "https://cdn11.bigcommerce.com/s-mpabgyqav0/images/stencil/1280x1280/products/312/2455/Indoor_-_THCa_Alien_Apple_Kush_Potency__33040.1690981203.jpg?c=1",
      "https://cdn11.bigcommerce.com/s-mpabgyqav0/images/stencil/1280x1280/products/312/2454/Indoor_-_THCa_Alien_Apple_Kush_Terpenes__21399.1690981203.jpg?c=1"
    ],
    "terpenes": [
      {
        "pct": "NaN",
        "originalText": "PPM PPM PPM mg/g",
        "name": "PPM",
        "mgg": "PPM"
      },
      {
        "pct": "2.728",
        "originalText": "Total 27276.865 27.277",
        "name": "Total",
        "mgg": "27276.865"
      },
      {
        "pct": "0.694",
        "originalText": "Limonene 0.750 3.000 6935.601 6.936",
        "name": "Limonene",
        "mgg": "6935.601"
      },
      {
        "pct": "0.592",
        "originalText": "B-Myrcene 0.750 3.000 5920.756 5.921",
        "name": "Myrcene",
        "mgg": "5920.756"
      },
      {
        "pct": "0.554",
        "originalText": "Linalool 0.750 3.000 5542581 5.543",
        "name": "Linalool",
        "mgg": "5542581"
      },
      {
        "pct": "0.523",
        "originalText": "B-Caryophyllene 0.750 3.000 5232012 5.232",
        "name": "Caryophyllene",
        "mgg": "5232012"
      },
      {
        "pct": "0.153",
        "originalText": "a-Humulene 0.750 3.000 1526.008 1.526",
        "name": "Humulene",
        "mgg": "1526.008"
      },
      {
        "pct": "0.110",
        "originalText": "a-Pinene 0.750 3.000 1102.736 1.103",
        "name": "Pinene",
        "mgg": "1102.736"
      },
      {
        "pct": "0.034",
        "originalText": "Camphene 0.750 3.000 343.370 0.343",
        "name": "Camphene",
        "mgg": "343.370"
      },
      {
        "pct": "0.024",
        "originalText": "Borneol 0.750 3.000 236.072 0.236",
        "name": "Borneol",
        "mgg": "236.072"
      },
      {
        "pct": "0.015",
        "originalText": "«-Bisabolol 0.750 3.000 145.996 0.146",
        "name": "«-Bisabolol",
        "mgg": "145.996"
      },
      {
        "pct": "0.013",
        "originalText": "Terpinolene 0.750 3.000 135.353 0.135",
        "name": "Terpinolene",
        "mgg": "135.353"
      },
      {
        "pct": "0.000",
        "originalText": "a-Terpinene 0.750 3.000 <LOQ <LOQ",
        "name": "Terpinene",
        "mgg": 0
      },
      {
        "pct": "0.000",
        "originalText": "1,8-Cineole 0.750 3.000 <LOQ <LOQ",
        "name": "Eucalyptol",
        "mgg": 0
      },
      {
        "pct": "0.000",
        "originalText": "Carene 0.750 3.000 ND ND",
        "name": "Carene",
        "mgg": 0
      },
      {
        "pct": "NaN",
        "originalText": "Caryophyllene Oxide 3.000 3.000 >3.000 >0.003",
        "name": "Caryophyllene",
        "mgg": 0
      },
      {
        "pct": "0.008",
        "originalText": "Fenchone 0.750 3.000 75.713 0.076",
        "name": "Fenchone",
        "mgg": "75.713"
      },
      {
        "pct": "0.000",
        "originalText": "Citral 0.750 3.000 ND ND",
        "name": "Citral",
        "mgg": 0
      },
      {
        "pct": "0.000",
        "originalText": "Dihydrocarveol 0.750 3.000 ND ND",
        "name": "Dihydrocarveol",
        "mgg": 0
      },
      {
        "pct": "0.000",
        "originalText": "y-Terpinene 0.750 3.000 <LOQ <LOQ",
        "name": "γ-Terpinene",
        "mgg": 0
      },
      {
        "pct": "0.000",
        "originalText": "Menthol 0.750 3.000 ND ND",
        "name": "Menthol",
        "mgg": 0
      },
      {
        "pct": "0.000",
        "originalText": "Nerolidol 0.750 3.000 ND ND",
        "name": "Nerolidol",
        "mgg": 0
      },
      {
        "pct": "0.000",
        "originalText": "Ocimene 0.750 3.000 ND ND",
        "name": "Ocimene",
        "mgg": 0
      },
      {
        "pct": "0.000",
        "originalText": "Pulegone 0.750 3.000 ND ND",
        "name": "Pulegone",
        "mgg": 0
      },
      {
        "pct": "NaN",
        "originalText": "Unknown",
        "name": "Unknown",
        "mgg": "Unknown"
      }
    ],
    "vendor": "WNC",
    "cannabinoids": [
      {
        "pct": "21.482",
        "originalText": "Total 21.482 214824",
        "name": "Total Cannabinoids",
        "mgg": "214824"
      },
      {
        "pct": "20.227",
        "originalText": "A-9-Tetrahydrocannabinolic Acid (THCA-A) 0.0503 0.0754 20.227 202,271",
        "name": "Unreadable",
        "mgg": "202,271"
      },
      {
        "pct": "0.894",
        "originalText": "Cannabigerolic Acid (CBGA) 0.0503 0.0754 0894 8.935",
        "name": "CBGA",
        "mgg": "8.935"
      },
      {
        "pct": "0.252",
        "originalText": "A-9-Tetrahydrocannabinol (A-9 THC) 0.0503 0.0754 0.252 2523",
        "name": "Unreadable",
        "mgg": "2523"
      },
      {
        "pct": "0.110",
        "originalText": "Cannabichromenic Acid (CBCA) 0.0503 0.0754 0.110 1.095",
        "name": "CBCA",
        "mgg": "1.095"
      },
      {
        "pct": "0.000",
        "originalText": "A-8-Tetrahydrocannabinol (A-8 THC) 0.0503 0.0754 ND ND",
        "name": "Unreadable",
        "mgg": 0
      },
      {
        "pct": "0.000",
        "originalText": "A-9-Tetrahydrocannabiphorol (A-9-THCP) 0.0503 0.0754 ND ND",
        "name": "THCP",
        "mgg": 0
      },
      {
        "pct": "0.000",
        "originalText": "A-9-Tetrahydrocannabivarin (A-9-THCV) 0.0503 0.0754 ND ND",
        "name": "THCV",
        "mgg": 0
      },
      {
        "pct": "0.000",
        "originalText": "A-9-Tetrahydrocannabivarinic Acid (A-9-THCVA) 0.0332 0.0754 <LOQ <LOQ",
        "name": "Delta 9-THCVA",
        "mgg": 0
      },
      {
        "pct": "0.000",
        "originalText": "R-A-10-Tetrahydrocannabinol (R-A-10-THC) 0.0503 0.0754 ND ND",
        "name": "R-Delta 10-THC",
        "mgg": 0
      },
      {
        "pct": "0.000",
        "originalText": "$-A-10-Tetrahydrocannabinol (S-A-10-THC) 0.0503 0.0754 ND ND",
        "name": "S-Delta 10-THC",
        "mgg": 0
      },
      {
        "pct": "0.000",
        "originalText": "9R-Hexahydrocannabinol (9R-HHC) 0.0503 0.0754 ND ND",
        "name": "9R-HHC",
        "mgg": 0
      },
      {
        "pct": "0.000",
        "originalText": "9S-Hexahydrocannabinol (95-HHC) 0.0503 0.0754 ND ND",
        "name": "9S-HHC",
        "mgg": 0
      },
      {
        "pct": "0.000",
        "originalText": "Tetrahydrocannabinol Acetate (THCO) 0.0503 0.0754 ND ND",
        "name": "THC",
        "mgg": 0
      },
      {
        "pct": "0.000",
        "originalText": "Cannabidivarin (CBDV) 0.0503 0.0754 ND ND",
        "name": "CBDV",
        "mgg": 0
      },
      {
        "pct": "0.000",
        "originalText": "Cannabidivarinic Acid (CBDVA) 0.0503 0.0754 ND ND",
        "name": "CBDVA",
        "mgg": 0
      },
      {
        "pct": "0.000",
        "originalText": "Cannabidiol (CBD) 0.0503 0.0754 ND ND",
        "name": "CBD",
        "mgg": 0
      },
      {
        "pct": "0.000",
        "originalText": "Cannabidiolic Acid (CBDA) 0.0503 0.0754 <LOQ <L0Q",
        "name": "CBDA",
        "mgg": 0
      },
      {
        "pct": "0.000",
        "originalText": "Cannabigerol (CBG) 0.0332 0.0754 <LOQ <LOQ",
        "name": "CBG",
        "mgg": 0
      },
      {
        "pct": "0.000",
        "originalText": "Cannabinol (CBN) 0.0503 0.0754 ND ND",
        "name": "CBN",
        "mgg": 0
      },
      {
        "pct": "0.000",
        "originalText": "Cannabinolic Acid (CBNA) 0.0503 0.0754 ND ND",
        "name": "CBNA",
        "mgg": 0
      },
      {
        "pct": "0.000",
        "originalText": "Cannabichromene (CBC) 0.0503 0.0754 ND ND",
        "name": "CBC",
        "mgg": 0
      },
      {
        "pct": "NaN",
        "originalText": "HC = THCa * 0.877 + A9-THC:Total CBD = CBDa * 0.877 + CBD; LOQ = Limit of Quantitation; ND = Not Detected.",
        "name": "Unreadable",
        "mgg": "Detected."
      },
      {
        "pct": "NaN",
        "originalText": "Unknown",
        "name": "Unreadable",
        "mgg": 0
      }
    ],
    "variants": [
      "3.5 g"
    ],
    "title": "Alien Apple Kush",
    "url": "https://wnc-cbd.com/products/thca-alien-apple-kush-indoor-living-soil.html"
  },
  {
    "image": "https://cdn11.bigcommerce.com/s-mpabgyqav0/images/stencil/500x659/products/358/3183/Alpha_Runtz_-_1__46009.1693930862.jpg?c=1",
    "images": [
      "https://cdn11.bigcommerce.com/s-mpabgyqav0/images/stencil/1280x1280/products/358/3185/Indoor_-_THCa_Alpha_Runtz_Potency__35372.1693931022.jpg?c=1",
      "https://cdn11.bigcommerce.com/s-mpabgyqav0/images/stencil/1280x1280/products/358/3186/Indoor_-_THCa_Alpha_Runtz_Terepnes__89860.1693931022.jpg?c=1"
    ],
    "terpenes": [
      {
        "pct": "0.799",
        "originalText": "Total 7994.853 7.995",
        "name": "Total",
        "mgg": "7994.853"
      },
      {
        "pct": "0.455",
        "originalText": "B-Caryophyllene 0.750 3.000 4552.695 4553",
        "name": "Caryophyllene",
        "mgg": "4552.695"
      },
      {
        "pct": "0.122",
        "originalText": "a-Humulene 0.750 3.000 1224.791 1.225",
        "name": "Humulene",
        "mgg": "1224.791"
      },
      {
        "pct": "0.058",
        "originalText": "Linalool 0.750 3.000 577.578 0.578",
        "name": "Linalool",
        "mgg": "577.578"
      },
      {
        "pct": "0.056",
        "originalText": "B-Myrcene 0.750 3.000 562.893 0.563",
        "name": "Myrcene",
        "mgg": "562.893"
      },
      {
        "pct": "0.045",
        "originalText": "Limonene 0.750 3.000 445.583 0.446",
        "name": "Limonene",
        "mgg": "445.583"
      },
      {
        "pct": "0.021",
        "originalText": "1,8-Cineole 0.750 3.000 210.543 0.211",
        "name": "Eucalyptol",
        "mgg": "210.543"
      },
      {
        "pct": "0.011",
        "originalText": "a-Pinene 0.750 3.000 115.189 0.115",
        "name": "Pinene",
        "mgg": "115.189"
      },
      {
        "pct": "0.004",
        "originalText": "Borneol 0.750 3.000 42.620 0.043",
        "name": "Borneol",
        "mgg": "42.620"
      },
      {
        "pct": "0.003",
        "originalText": "Camphene 0.750 3.000 31.768 0.032",
        "name": "Camphene",
        "mgg": "31.768"
      },
      {
        "pct": "0.003",
        "originalText": "y-Terpinene 0.750 3.000 29.601 0.030",
        "name": "γ-Terpinene",
        "mgg": "29.601"
      },
      {
        "pct": "0.002",
        "originalText": "a-Terpinene 0.750 3.000 21837 0.022",
        "name": "Terpinene",
        "mgg": "21837"
      },
      {
        "pct": "0.000",
        "originalText": "a-Bisabolol 0.750 3.000 ND ND",
        "name": "Bisabolol",
        "mgg": 0
      },
      {
        "pct": "0.000",
        "originalText": "Carene 0.750 3.000 ND ND",
        "name": "Carene",
        "mgg": 0
      },
      {
        "pct": "NaN",
        "originalText": "Caryophyllene Oxide 3.000 3.000 >3.000 >0.003",
        "name": "Caryophyllene",
        "mgg": 0
      },
      {
        "pct": "0.002",
        "originalText": "Fenchone 0.750 3.000 19.219 0.019",
        "name": "Fenchone",
        "mgg": "19.219"
      },
      {
        "pct": "0.000",
        "originalText": "Citral 0.750 3.000 ND ND",
        "name": "Citral",
        "mgg": 0
      },
      {
        "pct": "0.000",
        "originalText": "Dihydrocarveol 0.750 3.000 ND ND",
        "name": "Dihydrocarveol",
        "mgg": 0
      },
      {
        "pct": "0.000",
        "originalText": "Menthol 0.750 3.000 ND ND",
        "name": "Menthol",
        "mgg": 0
      },
      {
        "pct": "0.000",
        "originalText": "Nerolidol 0.750 3.000 ND ND",
        "name": "Nerolidol",
        "mgg": 0
      },
      {
        "pct": "0.000",
        "originalText": "Ocimene 0.750 3.000 ND ND",
        "name": "Ocimene",
        "mgg": 0
      },
      {
        "pct": "0.000",
        "originalText": "Pulegone 0.750 3.000 ND ND",
        "name": "Pulegone",
        "mgg": 0
      },
      {
        "pct": "0.000",
        "originalText": "Terpinolene 0.750 3.000 <LOQ <LOQ",
        "name": "Terpinolene",
        "mgg": 0
      },
      {
        "pct": "NaN",
        "originalText": "Unknown",
        "name": "Unknown",
        "mgg": "Unknown"
      }
    ],
    "vendor": "WNC",
    "cannabinoids": [
      {
        "pct": "26.981",
        "originalText": "Total 26.981 269.806",
        "name": "Total Cannabinoids",
        "mgg": "269.806"
      },
      {
        "pct": "0.489",
        "originalText": "Cannabigerolic Acid (CBGA) 0.0485 0.0728 0.489 4893",
        "name": "CBGA",
        "mgg": "4893"
      },
      {
        "pct": "0.167",
        "originalText": "A-9-Tetrahydrocannabinol (A-9 THC) 0.0485 0.0728 0.167 1.670",
        "name": "Unreadable",
        "mgg": "1.670"
      },
      {
        "pct": "0.121",
        "originalText": "Cannabichromenic Acid (CBCA) 0.0485 0.0728 0.121 1214",
        "name": "CBCA",
        "mgg": "1214"
      },
      {
        "pct": "0.076",
        "originalText": "A-9-Tetrahydrocannabivarinic Acid (A-2-THCVA) 0.0485 0.0728 0.076 0.757",
        "name": "Delta 9-THCVA",
        "mgg": "0.757"
      },
      {
        "pct": "0.026",
        "originalText": "A-9-Tetrahydrocannabinolic Acid (THCA-A) 0.0485 0.0728 26,127 261.272",
        "name": "Unreadable",
        "mgg": "261.272"
      },
      {
        "pct": "0.000",
        "originalText": "A-8-Tetrahydrocannabinol (A-8 THC) 0.0485 0.0728 ND ND",
        "name": "Unreadable",
        "mgg": 0
      },
      {
        "pct": "0.000",
        "originalText": "A-9-Tetrahydrocannabiphorol (A-9-THCP) 0.0485 0.0728 ND ND",
        "name": "THCP",
        "mgg": 0
      },
      {
        "pct": "0.000",
        "originalText": "A-9-Tetrahydrocannabivarin (A-9-THCV) 0.0485 0.0728 ND ND",
        "name": "THCV",
        "mgg": 0
      },
      {
        "pct": "0.000",
        "originalText": "R-A-10-Tetrahydrocannabinol (R-A-10-THC) 0.0485 0.0728 ND ND",
        "name": "R-Delta 10-THC",
        "mgg": 0
      },
      {
        "pct": "0.000",
        "originalText": "$-A-10-Tetrahydrocannabinol (S-A-10-THC) 0.0485 0.0728 ND ND",
        "name": "S-Delta 10-THC",
        "mgg": 0
      },
      {
        "pct": "0.000",
        "originalText": "9R-Hexahydrocannabinol (9R-HHC) 0.0485 0.0728 ND ND",
        "name": "9R-HHC",
        "mgg": 0
      },
      {
        "pct": "0.000",
        "originalText": "9S-Hexahydrocannabinol (95-HHC) 0.0485 0.0728 ND ND",
        "name": "9S-HHC",
        "mgg": 0
      },
      {
        "pct": "0.000",
        "originalText": "Tetrahydrocannabinol Acetate (THCO) 0.0485 0.0728 ND ND",
        "name": "THC",
        "mgg": 0
      },
      {
        "pct": "0.000",
        "originalText": "Cannabidivarin (CBDV) 0.0485 0.0728 ND ND",
        "name": "CBDV",
        "mgg": 0
      },
      {
        "pct": "0.000",
        "originalText": "Cannabidivarinic Acid (CBDVA) 0.0485 0.0728 ND ND",
        "name": "CBDVA",
        "mgg": 0
      },
      {
        "pct": "0.000",
        "originalText": "Cannabidiol (CBD) 0.0485 0.0728 ND ND",
        "name": "CBD",
        "mgg": 0
      },
      {
        "pct": "0.000",
        "originalText": "Cannabidiolic Acid (CBDA) 0.0485 0.0728 ND ND",
        "name": "CBDA",
        "mgg": 0
      },
      {
        "pct": "0.000",
        "originalText": "Cannabigerol (CBG) 0.0485 0.0728 ND ND",
        "name": "CBG",
        "mgg": 0
      },
      {
        "pct": "0.000",
        "originalText": "Cannabinol (CBN) 0.0485 0.0728 ND ND",
        "name": "CBN",
        "mgg": 0
      },
      {
        "pct": "0.000",
        "originalText": "Cannabinolic Acid (CBNA) 0.0320 0.0728 <LOQ <LOQ",
        "name": "CBNA",
        "mgg": 0
      },
      {
        "pct": "0.000",
        "originalText": "Cannabichromene (CBC) 0.0485 0.0728 ND ND",
        "name": "CBC",
        "mgg": 0
      },
      {
        "pct": "NaN",
        "originalText": "HC = THCa * 0.877 + A9-THC:Total CBD = CBDa * 0.877 + CBD; LOQ = Limit of Quantitation; ND = Not Detected.",
        "name": "Unreadable",
        "mgg": "Detected."
      },
      {
        "pct": "NaN",
        "originalText": "Unknown",
        "name": "Unreadable",
        "mgg": 0
      }
    ],
    "variants": [
      "3.5 g",
      "7 g"
    ],
    "title": "Alpha Runtz",
    "url": "https://wnc-cbd.com/products/thca-alpha-runtz-indoor-living-soil.html"
  },
  {
    "image": "https://cdn11.bigcommerce.com/s-mpabgyqav0/images/stencil/500x659/products/313/2467/Black_Cherry_Gelato_-_1__71273.1689100125.jpg?c=1",
    "images": [
      "https://cdn11.bigcommerce.com/s-mpabgyqav0/images/stencil/1280x1280/products/313/2470/Indoor_-_THCa_Black_Cherry_Gelato_Potency__50136.1689100186.jpg?c=1",
      "https://cdn11.bigcommerce.com/s-mpabgyqav0/images/stencil/1280x1280/products/313/2469/Indoor_-_THCa_Black_Cherry_Gelato_Terpenes__76784.1689100186.jpg?c=1"
    ],
    "terpenes": [
      {
        "pct": "1.048",
        "originalText": "Total 10479.936 10.480",
        "name": "Total",
        "mgg": "10479.936"
      },
      {
        "pct": "0.295",
        "originalText": "B-Myrcene 0.750 3.000 2946.048 2.946",
        "name": "Myrcene",
        "mgg": "2946.048"
      },
      {
        "pct": "0.269",
        "originalText": "Limonene 0.750 3.000 2687.301 2.687",
        "name": "Limonene",
        "mgg": "2687.301"
      },
      {
        "pct": "0.234",
        "originalText": "Linalool 0.750 3.000 2339.159 2.339",
        "name": "Linalool",
        "mgg": "2339.159"
      },
      {
        "pct": "0.139",
        "originalText": "a-Humulene 0.750 3.000 1393.025 1.393",
        "name": "Humulene",
        "mgg": "1393.025"
      },
      {
        "pct": "0.037",
        "originalText": "«-Bisabolol 0.750 3.000 374.257 0.374",
        "name": "«-Bisabolol",
        "mgg": "374.257"
      },
      {
        "pct": "0.037",
        "originalText": "a-Pinene 0.750 3.000 370.962 0.371",
        "name": "Pinene",
        "mgg": "370.962"
      },
      {
        "pct": "0.012",
        "originalText": "Camphene 0.750 3.000 117.013 0.117",
        "name": "Camphene",
        "mgg": "117.013"
      },
      {
        "pct": "0.009",
        "originalText": "Borneol 0.750 3.000 88.210 0.088",
        "name": "Borneol",
        "mgg": "88.210"
      },
      {
        "pct": "0.005",
        "originalText": "Fenchone 0.750 3.000 46.271 0.046",
        "name": "Fenchone",
        "mgg": "46.271"
      },
      {
        "pct": "0.005",
        "originalText": "Terpinolene 0.750 3.000 49.279 0.049",
        "name": "Terpinolene",
        "mgg": "49.279"
      },
      {
        "pct": "0.000",
        "originalText": "a-Terpinene 0.750 3.000 ND ND",
        "name": "Terpinene",
        "mgg": 0
      },
      {
        "pct": "0.000",
        "originalText": "1,8-Cineole 0.750 3.000 <LOQ <LOQ",
        "name": "Eucalyptol",
        "mgg": 0
      },
      {
        "pct": "0.000",
        "originalText": "B-Caryophyllene 0.750 3.000 ND ND",
        "name": "Caryophyllene",
        "mgg": 0
      },
      {
        "pct": "0.000",
        "originalText": "Carene 0.750 3.000 ND ND",
        "name": "Carene",
        "mgg": 0
      },
      {
        "pct": "NaN",
        "originalText": "Caryophyllene Oxide 3.000 3.000 >3.000 >0.003",
        "name": "Caryophyllene",
        "mgg": 0
      },
      {
        "pct": "0.000",
        "originalText": "Citral 0.750 3.000 ND ND",
        "name": "Citral",
        "mgg": 0
      },
      {
        "pct": "0.000",
        "originalText": "Dihydrocarveol 0.750 3.000 ND ND",
        "name": "Dihydrocarveol",
        "mgg": 0
      },
      {
        "pct": "0.000",
        "originalText": "y-Terpinene 0.750 3.000 <LOQ <LOQ",
        "name": "γ-Terpinene",
        "mgg": 0
      },
      {
        "pct": "0.000",
        "originalText": "Menthol 0.750 3.000 ND ND",
        "name": "Menthol",
        "mgg": 0
      },
      {
        "pct": "0.000",
        "originalText": "Nerolidol 0.750 3.000 ND ND",
        "name": "Nerolidol",
        "mgg": 0
      },
      {
        "pct": "0.000",
        "originalText": "Ocimene 0.750 3.000 ND ND",
        "name": "Ocimene",
        "mgg": 0
      },
      {
        "pct": "0.000",
        "originalText": "Pulegone 0.750 3.000 ND ND",
        "name": "Pulegone",
        "mgg": 0
      },
      {
        "pct": "NaN",
        "originalText": "Unknown",
        "name": "Unknown",
        "mgg": "Unknown"
      }
    ],
    "vendor": "WNC",
    "cannabinoids": [
      {
        "pct": "24.505",
        "originalText": "Total 24505 245054",
        "name": "Total Cannabinoids",
        "mgg": "245054"
      },
      {
        "pct": "22.747",
        "originalText": "A-9-Tetrahydrocannabinolic Acid (THCA-A) 0.0493 0.0739 22.747 227.468",
        "name": "Unreadable",
        "mgg": "227.468"
      },
      {
        "pct": "1.202",
        "originalText": "Cannabigerolic Acid (CBGA) 0.0493 0.0739 1202 12,020",
        "name": "CBGA",
        "mgg": "12,020"
      },
      {
        "pct": "0.267",
        "originalText": "A-9-Tetrahydrocannabinol (A-9 THC) 0.0493 0.0739 0.267 2670",
        "name": "Unreadable",
        "mgg": "2670"
      },
      {
        "pct": "0.170",
        "originalText": "Cannabigerol (CBG) 0.0493 0.0739 0.170 1.704",
        "name": "CBG",
        "mgg": "1.704"
      },
      {
        "pct": "0.119",
        "originalText": "A-9-Tetrahydrocannabivarinic Acid (A-2-THCVA) 0.0493 0.0739 0.119 1192",
        "name": "Delta 9-THCVA",
        "mgg": "1192"
      },
      {
        "pct": "0.000",
        "originalText": "A-8-Tetrahydrocannabinol (A-8 THC) 0.0493 0.0739 ND ND",
        "name": "Unreadable",
        "mgg": 0
      },
      {
        "pct": "0.000",
        "originalText": "A-9-Tetrahydrocannabiphorol (A-9-THCP) 0.0493 0.0739 ND ND",
        "name": "THCP",
        "mgg": 0
      },
      {
        "pct": "0.000",
        "originalText": "A-9-Tetrahydrocannabivarin (A-9-THCV) 0.0493 0.0739 ND ND",
        "name": "THCV",
        "mgg": 0
      },
      {
        "pct": "0.000",
        "originalText": "R-A-10-Tetrahydrocannabinol (R-A-10-THC) 0.0493 0.0739 ND ND",
        "name": "R-Delta 10-THC",
        "mgg": 0
      },
      {
        "pct": "0.000",
        "originalText": "$-A-10-Tetrahydrocannabinol (S-A-10-THC) 0.0493 0.0739 ND ND",
        "name": "S-Delta 10-THC",
        "mgg": 0
      },
      {
        "pct": "0.000",
        "originalText": "9R-Hexahydrocannabinol (9R-HHC) 0.0493 0.0739 ND ND",
        "name": "9R-HHC",
        "mgg": 0
      },
      {
        "pct": "0.000",
        "originalText": "9S-Hexahydrocannabinol (95-HHC) 0.0493 0.0739 ND ND",
        "name": "9S-HHC",
        "mgg": 0
      },
      {
        "pct": "0.000",
        "originalText": "Tetrahydrocannabinol Acetate (THCO) 0.0493 0.0739 ND ND",
        "name": "THC",
        "mgg": 0
      },
      {
        "pct": "0.000",
        "originalText": "Cannabidivarin (CBDV) 0.0493 0.0739 ND ND",
        "name": "CBDV",
        "mgg": 0
      },
      {
        "pct": "0.000",
        "originalText": "Cannabidivarinic Acid (CBDVA) 0.0493 0.0739 ND ND",
        "name": "CBDVA",
        "mgg": 0
      },
      {
        "pct": "0.000",
        "originalText": "Cannabidiol (CBD) 0.0493 0.0739 ND ND",
        "name": "CBD",
        "mgg": 0
      },
      {
        "pct": "0.000",
        "originalText": "Cannabidiolic Acid (CBDA) 0.0493 0.0739 <LOQ <L0Q",
        "name": "CBDA",
        "mgg": 0
      },
      {
        "pct": "0.000",
        "originalText": "Cannabinol (CBN) 0.0493 0.0739 ND ND",
        "name": "CBN",
        "mgg": 0
      },
      {
        "pct": "0.000",
        "originalText": "Cannabinolic Acid (CBNA) 0.0493 0.0739 ND ND",
        "name": "CBNA",
        "mgg": 0
      },
      {
        "pct": "0.000",
        "originalText": "Cannabichromene (CBC) 0.0493 0.0739 ND ND",
        "name": "CBC",
        "mgg": 0
      },
      {
        "pct": "0.000",
        "originalText": "Cannabichromenic Acid (CBCA) 0.0493 0.0739 <LOQ <LOQ",
        "name": "CBCA",
        "mgg": 0
      },
      {
        "pct": "NaN",
        "originalText": "HC = THCa * 0.877 + A9-THC:Total CBD = CBDa * 0.877 + CBD; LOQ = Limit of Quantitation; ND = Not Detected.",
        "name": "Unreadable",
        "mgg": "Detected."
      },
      {
        "pct": "NaN",
        "originalText": "Unknown",
        "name": "Unreadable",
        "mgg": 0
      }
    ],
    "variants": [
      "3.5 g",
      "7 g"
    ],
    "title": "Black Cherry Gelato",
    "url": "https://wnc-cbd.com/products/thca-black-cherry-gelato-indoor-hydro.html"
  },
  {
    "image": "https://cdn11.bigcommerce.com/s-mpabgyqav0/images/stencil/500x659/products/116/3208/Blue_Unicorn_-_1__99546.1693938120.jpg?c=1",
    "images": [
      "https://cdn11.bigcommerce.com/s-mpabgyqav0/images/stencil/1280x1280/products/116/3207/Indoor_-_THCa_Blue_Unicorn_Potency_NEW__06739.1693938112.jpg?c=1",
      "https://cdn11.bigcommerce.com/s-mpabgyqav0/images/stencil/1280x1280/products/116/3206/Indoor_-_THCa_Blue_Unicorn_Terpenes_NEW__07590.1693938112.jpg?c=1"
    ],
    "terpenes": [
      {
        "pct": "NaN",
        "originalText": "PPM PPM PPM mg/g",
        "name": "PPM",
        "mgg": "PPM"
      },
      {
        "pct": "1.338",
        "originalText": "Total 13375.512 13.376",
        "name": "Total",
        "mgg": "13375.512"
      },
      {
        "pct": "0.423",
        "originalText": "Linalool 0.750 3.000 4227.363 4227",
        "name": "Linalool",
        "mgg": "4227.363"
      },
      {
        "pct": "0.383",
        "originalText": "B-Caryophyllene 0.750 3.000 3825.879 3.826",
        "name": "Caryophyllene",
        "mgg": "3825.879"
      },
      {
        "pct": "0.175",
        "originalText": "B-Myrcene 0.750 3.000 1749.048 1.749",
        "name": "Myrcene",
        "mgg": "1749.048"
      },
      {
        "pct": "0.154",
        "originalText": "Limonene 0.750 3.000 1544.110 1544",
        "name": "Limonene",
        "mgg": "1544.110"
      },
      {
        "pct": "0.115",
        "originalText": "a-Humulene 0.750 3.000 1148.213 1.148",
        "name": "Humulene",
        "mgg": "1148.213"
      },
      {
        "pct": "0.029",
        "originalText": "«-Bisabolol 0.750 3.000 295.247 0.295",
        "name": "«-Bisabolol",
        "mgg": "295.247"
      },
      {
        "pct": "0.018",
        "originalText": "a-Pinene 0.750 3.000 178.772 0.179",
        "name": "Pinene",
        "mgg": "178.772"
      },
      {
        "pct": "0.011",
        "originalText": "Borneol 0.750 3.000 109.189 0.109",
        "name": "Borneol",
        "mgg": "109.189"
      },
      {
        "pct": "0.007",
        "originalText": "Camphene 0.750 3.000 66.660 0.067",
        "name": "Camphene",
        "mgg": "66.660"
      },
      {
        "pct": "0.003",
        "originalText": "Terpinolene 0.750 3.000 29.863 0.030",
        "name": "Terpinolene",
        "mgg": "29.863"
      },
      {
        "pct": "0.000",
        "originalText": "a-Terpinene 0.750 3.000 <LOQ <LOQ",
        "name": "Terpinene",
        "mgg": 0
      },
      {
        "pct": "0.000",
        "originalText": "1,8-Cineole 0.750 3.000 <LOQ <LOQ",
        "name": "Eucalyptol",
        "mgg": 0
      },
      {
        "pct": "0.000",
        "originalText": "Carene 0.750 3.000 ND ND",
        "name": "Carene",
        "mgg": 0
      },
      {
        "pct": "NaN",
        "originalText": "Caryophyllene Oxide 3.000 3.000 >3.000 >0.003",
        "name": "Caryophyllene",
        "mgg": 0
      },
      {
        "pct": "0.004",
        "originalText": "Fenchone 0.750 3.000 41871 0.042",
        "name": "Fenchone",
        "mgg": "41871"
      },
      {
        "pct": "0.000",
        "originalText": "Citral 0.750 3.000 ND ND",
        "name": "Citral",
        "mgg": 0
      },
      {
        "pct": "0.000",
        "originalText": "Dihydrocarveol 0.750 3.000 ND ND",
        "name": "Dihydrocarveol",
        "mgg": 0
      },
      {
        "pct": "0.000",
        "originalText": "y-Terpinene 0.750 3.000 <LOQ <LOQ",
        "name": "γ-Terpinene",
        "mgg": 0
      },
      {
        "pct": "0.000",
        "originalText": "Menthol 0.750 3.000 ND ND",
        "name": "Menthol",
        "mgg": 0
      },
      {
        "pct": "0.000",
        "originalText": "Nerolidol 0.750 3.000 ND ND",
        "name": "Nerolidol",
        "mgg": 0
      },
      {
        "pct": "0.000",
        "originalText": "Ocimene 0.750 3.000 ND ND",
        "name": "Ocimene",
        "mgg": 0
      },
      {
        "pct": "0.000",
        "originalText": "Pulegone 0.750 3.000 ND ND",
        "name": "Pulegone",
        "mgg": 0
      },
      {
        "pct": "NaN",
        "originalText": "Unknown",
        "name": "Unknown",
        "mgg": "Unknown"
      }
    ],
    "vendor": "WNC",
    "cannabinoids": [
      {
        "pct": "25.978",
        "originalText": "Total 25978 259.784",
        "name": "Total Cannabinoids",
        "mgg": "259.784"
      },
      {
        "pct": "24.224",
        "originalText": "A-9-Tetrahydrocannabinolic Acid (THCA-A) 0.0490 0.0735 24224 242235",
        "name": "Unreadable",
        "mgg": "242235"
      },
      {
        "pct": "1.266",
        "originalText": "Cannabigerolic Acid (CBGA) 0.0490 0.0735 1266 12657",
        "name": "CBGA",
        "mgg": "12657"
      },
      {
        "pct": "0.232",
        "originalText": "Cannabigerol (CBG) 0.0490 0.0735 0232 2.324",
        "name": "CBG",
        "mgg": "2.324"
      },
      {
        "pct": "0.174",
        "originalText": "A-9-Tetrahydrocannabinol (A-9 THC) 0.0490 0.0735 0.174 1735",
        "name": "Unreadable",
        "mgg": "1735"
      },
      {
        "pct": "0.083",
        "originalText": "A-9-Tetrahydrocannabivarinic Acid (A-9-THCVA) 0.04%90 0.0735 0.083 0.833",
        "name": "Delta 9-THCVA",
        "mgg": "0.833"
      },
      {
        "pct": "0.000",
        "originalText": "A-8-Tetrahydrocannabinol (A-8 THC) 0.0490 0.0735 ND ND",
        "name": "Unreadable",
        "mgg": 0
      },
      {
        "pct": "0.000",
        "originalText": "A-9-Tetrahydrocannabiphorol (A-9-THCP) 0.0490 0.0735 ND ND",
        "name": "THCP",
        "mgg": 0
      },
      {
        "pct": "0.000",
        "originalText": "A-9-Tetrahydrocannabivarin (A-9-THCV) 0.0490 0.0735 ND ND",
        "name": "THCV",
        "mgg": 0
      },
      {
        "pct": "0.000",
        "originalText": "R-A-10-Tetrahydrocannabinol (R-A-10-THC) 0.0490 0.0735 ND ND",
        "name": "R-Delta 10-THC",
        "mgg": 0
      },
      {
        "pct": "0.000",
        "originalText": "$-A-10-Tetrahydrocannabinol (S-A-10-THC) 0.0490 0.0735 ND ND",
        "name": "S-Delta 10-THC",
        "mgg": 0
      },
      {
        "pct": "0.000",
        "originalText": "9R-Hexahydrocannabinol (9R-HHC) 0.0490 0.0735 ND ND",
        "name": "9R-HHC",
        "mgg": 0
      },
      {
        "pct": "0.000",
        "originalText": "9S-Hexahydrocannabinol (95-HHC) 0.0490 0.0735 ND ND",
        "name": "9S-HHC",
        "mgg": 0
      },
      {
        "pct": "0.000",
        "originalText": "Tetrahydrocannabinol Acetate (THCO) 0.0490 0.0735 ND ND",
        "name": "THC",
        "mgg": 0
      },
      {
        "pct": "0.000",
        "originalText": "Cannabidivarin (CBDV) 0.0490 0.0735 ND ND",
        "name": "CBDV",
        "mgg": 0
      },
      {
        "pct": "0.000",
        "originalText": "Cannabidivarinic Acid (CBDVA) 0.0490 0.0735 ND ND",
        "name": "CBDVA",
        "mgg": 0
      },
      {
        "pct": "0.000",
        "originalText": "Cannabidiol (CBD) 0.0490 0.0735 ND ND",
        "name": "CBD",
        "mgg": 0
      },
      {
        "pct": "0.000",
        "originalText": "Cannabidiolic Acid (CBDA) 0.0353 0.0735 <LOQ <L0Q",
        "name": "CBDA",
        "mgg": 0
      },
      {
        "pct": "0.000",
        "originalText": "Cannabinol (CBN) 0.0490 0.0735 ND ND",
        "name": "CBN",
        "mgg": 0
      },
      {
        "pct": "0.000",
        "originalText": "Cannabinolic Acid (CBNA) 0.0490 0.0735 ND ND",
        "name": "CBNA",
        "mgg": 0
      },
      {
        "pct": "0.000",
        "originalText": "Cannabichromene (CBC) 0.0490 0.0735 ND ND",
        "name": "CBC",
        "mgg": 0
      },
      {
        "pct": "0.000",
        "originalText": "Cannabichromenic Acid (CBCA) 0.0353 0.0735 <LOQ <LOQ",
        "name": "CBCA",
        "mgg": 0
      },
      {
        "pct": "NaN",
        "originalText": "HC = THCa * 0.877 + A9-THC:Total CBD = CBDa * 0.877 + CBD; LOQ = Limit of Quantitation; ND = Not Detected.",
        "name": "Unreadable",
        "mgg": "Detected."
      },
      {
        "pct": "NaN",
        "originalText": "Unknown",
        "name": "Unreadable",
        "mgg": 0
      }
    ],
    "variants": [
      "3.5 g"
    ],
    "title": "Blue Unicorn",
    "url": "https://wnc-cbd.com/thca-blue-unicorn-indoor/"
  },
  {
    "image": "https://cdn11.bigcommerce.com/s-mpabgyqav0/images/stencil/500x659/products/372/3391/Bread_Butter_-_1__30350.1695145967.jpg?c=1",
    "images": [
      "https://cdn11.bigcommerce.com/s-mpabgyqav0/images/stencil/1280x1280/products/372/3393/Indoor_-_THCa_Bread_Butter_Potency__50328.1695147249.jpg?c=1",
      "https://cdn11.bigcommerce.com/s-mpabgyqav0/images/stencil/1280x1280/products/372/3394/Indoor_-_THCa_Bread_Butter_Terpenes__54667.1695147249.jpg?c=1"
    ],
    "terpenes": [
      {
        "pct": "NaN",
        "originalText": "PPM PPM PPM mg/g",
        "name": "PPM",
        "mgg": "PPM"
      },
      {
        "pct": "1.418",
        "originalText": "Total 14183.330 14.183",
        "name": "Total",
        "mgg": "14183.330"
      },
      {
        "pct": "0.594",
        "originalText": "B-Caryophyllene 0.750 3.000 5935.150 5.935",
        "name": "Caryophyllene",
        "mgg": "5935.150"
      },
      {
        "pct": "0.183",
        "originalText": "a-Humulene 0.750 3.000 1832.469 1.832",
        "name": "Humulene",
        "mgg": "1832.469"
      },
      {
        "pct": "0.178",
        "originalText": "Linalool 0.750 3.000 1781431 1.781",
        "name": "Linalool",
        "mgg": "1781431"
      },
      {
        "pct": "0.083",
        "originalText": "a-Pinene 0.750 3.000 827.942 0.828",
        "name": "Pinene",
        "mgg": "827.942"
      },
      {
        "pct": "0.060",
        "originalText": "Ocimene 0.750 3.000 598.117 0.598",
        "name": "Ocimene",
        "mgg": "598.117"
      },
      {
        "pct": "0.032",
        "originalText": "Borneol 0.750 3.000 317.630 0.318",
        "name": "Borneol",
        "mgg": "317.630"
      },
      {
        "pct": "0.022",
        "originalText": "Fenchone 0.750 3.000 219.507 0.220",
        "name": "Fenchone",
        "mgg": "219.507"
      },
      {
        "pct": "0.016",
        "originalText": "Camphene 0.750 3.000 163.487 0.163",
        "name": "Camphene",
        "mgg": "163.487"
      },
      {
        "pct": "0.015",
        "originalText": "1,8-Cineole 0.750 3.000 148.483 0.148",
        "name": "Eucalyptol",
        "mgg": "148.483"
      },
      {
        "pct": "0.006",
        "originalText": "Terpinolene 0.750 3.000 64.280 0.064",
        "name": "Terpinolene",
        "mgg": "64.280"
      },
      {
        "pct": "0.003",
        "originalText": "y-Terpinene 0.750 3.000 26.242 0.026",
        "name": "γ-Terpinene",
        "mgg": "26.242"
      },
      {
        "pct": "0.002",
        "originalText": "a-Terpinene 0.750 3.000 20.792 0.021",
        "name": "Terpinene",
        "mgg": "20.792"
      },
      {
        "pct": "0.002",
        "originalText": "Citral 0.750 3.000 15.937 0.016",
        "name": "Citral",
        "mgg": "15.937"
      },
      {
        "pct": "0.000",
        "originalText": "«-Bisabolol 0.750 3.000 ND ND",
        "name": "«-Bisabolol",
        "mgg": 0
      },
      {
        "pct": "0.000",
        "originalText": "B-Myrcene 0.750 3.000 ND ND",
        "name": "Myrcene",
        "mgg": 0
      },
      {
        "pct": "0.000",
        "originalText": "Carene 0.750 3.000 ND ND",
        "name": "Carene",
        "mgg": 0
      },
      {
        "pct": "NaN",
        "originalText": "Caryophyllene Oxide 3.000 3.000 >3.000 >0.003",
        "name": "Caryophyllene",
        "mgg": 0
      },
      {
        "pct": "0.000",
        "originalText": "Dihydrocarveol 0.750 3.000 ND ND",
        "name": "Dihydrocarveol",
        "mgg": 0
      },
      {
        "pct": "0.000",
        "originalText": "Limonene 0.750 3.000 2053.486 2,053",
        "name": "Limonene",
        "mgg": "2053.486"
      },
      {
        "pct": "0.000",
        "originalText": "Menthol 0.750 3.000 ND ND",
        "name": "Menthol",
        "mgg": 0
      },
      {
        "pct": "0.000",
        "originalText": "Nerolidol 0.750 3.000 ND ND",
        "name": "Nerolidol",
        "mgg": 0
      },
      {
        "pct": "0.000",
        "originalText": "Pulegone 0.750 3.000 ND ND",
        "name": "Pulegone",
        "mgg": 0
      },
      {
        "pct": "NaN",
        "originalText": "Unknown",
        "name": "Unknown",
        "mgg": "Unknown"
      }
    ],
    "vendor": "WNC",
    "cannabinoids": [
      {
        "pct": "21.638",
        "originalText": "Total 21.638 216.384",
        "name": "Total Cannabinoids",
        "mgg": "216.384"
      },
      {
        "pct": "0.599",
        "originalText": "Cannabigerolic Acid (CBGA) 0.0481 0.0721 0599 5.990",
        "name": "CBGA",
        "mgg": "5.990"
      },
      {
        "pct": "0.157",
        "originalText": "Cannabichromenic Acid (CBCA) 0.0481 00721 0.157 1567",
        "name": "CBCA",
        "mgg": "1567"
      },
      {
        "pct": "0.105",
        "originalText": "A-9-Tetrahydrocannabinol (A-9 THC) 0.0481 0.0721 0.105 1.048",
        "name": "Unreadable",
        "mgg": "1.048"
      },
      {
        "pct": "0.105",
        "originalText": "A-9-Tetrahydrocannabivarinic Acid (A-9-THCVA) 0.0481 0.0721 0.105 1048",
        "name": "Delta 9-THCVA",
        "mgg": "1048"
      },
      {
        "pct": "0.020",
        "originalText": "A-9-Tetrahydrocannabinolic Acid (THCA-A) 0.0481 0.0721 20,673 206,731",
        "name": "Unreadable",
        "mgg": "206,731"
      },
      {
        "pct": "0.000",
        "originalText": "A-8-Tetrahydrocannabinol (A-8 THC) 0.0481 0.0721 ND ND",
        "name": "Unreadable",
        "mgg": 0
      },
      {
        "pct": "0.000",
        "originalText": "A-9-Tetrahydrocannabiphorol (A-9-THCP) 0.0481 00721 ND ND",
        "name": "THCP",
        "mgg": 0
      },
      {
        "pct": "0.000",
        "originalText": "A-9-Tetrahydrocannabivarin (A-9-THCV) 0.0481 0.0721 ND ND",
        "name": "THCV",
        "mgg": 0
      },
      {
        "pct": "0.000",
        "originalText": "R-A-10-Tetrahydrocannabinol (R-A-10-THC) 0.0481 0.0721 ND ND",
        "name": "R-Delta 10-THC",
        "mgg": 0
      },
      {
        "pct": "0.000",
        "originalText": "$-A-10-Tetrahydrocannabinol (S-A-10-THC) 0.0481 0.0721 ND ND",
        "name": "S-Delta 10-THC",
        "mgg": 0
      },
      {
        "pct": "0.000",
        "originalText": "9R-Hexahydrocannabinol (9R-HHC) 0.0481 0.0721 ND ND",
        "name": "9R-HHC",
        "mgg": 0
      },
      {
        "pct": "0.000",
        "originalText": "9S-Hexahydrocannabinol (95-HHC) 0.0481 0.0721 ND ND",
        "name": "9S-HHC",
        "mgg": 0
      },
      {
        "pct": "0.000",
        "originalText": "Tetrahydrocannabinol Acetate (THCO) 0.0481 0.0721 ND ND",
        "name": "THC",
        "mgg": 0
      },
      {
        "pct": "0.000",
        "originalText": "Cannabidivarin (CBDV) 0.0481 0.0721 ND ND",
        "name": "CBDV",
        "mgg": 0
      },
      {
        "pct": "0.000",
        "originalText": "Cannabidivarinic Acid (CBDVA) 0.0481 0.0721 ND ND",
        "name": "CBDVA",
        "mgg": 0
      },
      {
        "pct": "0.000",
        "originalText": "Cannabidiol (CBD) 0.0481 0.0721 ND ND",
        "name": "CBD",
        "mgg": 0
      },
      {
        "pct": "0.000",
        "originalText": "Cannabidiolic Acid (CBDA) 0.0221 0.0721 <LOQ <L0Q",
        "name": "CBDA",
        "mgg": 0
      },
      {
        "pct": "0.000",
        "originalText": "Cannabigerol (CBG) 0.0221 0.0721 <LOQ <LOQ",
        "name": "CBG",
        "mgg": 0
      },
      {
        "pct": "0.000",
        "originalText": "Cannabinol (CBN) 0.0481 0.0721 ND ND",
        "name": "CBN",
        "mgg": 0
      },
      {
        "pct": "0.000",
        "originalText": "Cannabinolic Acid (CBNA) 0.0481 0.0721 ND ND",
        "name": "CBNA",
        "mgg": 0
      },
      {
        "pct": "0.000",
        "originalText": "Cannabichromene (CBC) 0.0481 0.0721 ND ND",
        "name": "CBC",
        "mgg": 0
      },
      {
        "pct": "NaN",
        "originalText": "HC = THCa * 0.877 + A9-THC:Total CBD = CBDa * 0.877 + CBD; LOQ = Limit of Quantitation; ND = Not Detected.",
        "name": "Unreadable",
        "mgg": "Detected."
      },
      {
        "pct": "NaN",
        "originalText": "Unknown",
        "name": "Unreadable",
        "mgg": 0
      }
    ],
    "variants": [
      "3.5 g",
      "7 g",
      "14 g smalls/minis"
    ],
    "title": "Bread + Butter",
    "url": "https://wnc-cbd.com/products/thca-bread-butter-indoor-living-soil.html"
  }
]